Arq. de Comp. I/Atividades_Guais/2024-2_arq1_guia_09/clock.v
/*
    -identificação: 

Clock.v - 27 / 09 / 2024

Nome: Davi Cândido de Almeida
Matricula: 857859
Código de Pessoa: 1527368

*/

/// ---------------------------
// -- test clock generator (1)
// ---------------------------
module clock ( output clk );

    reg clk;

    initial
        begin
         clk = 1'b0;
        end

    always
        begin
         #12 clk = ~clk;
        end
endmodule // clock ( )



/*
    -Notas:

Para compilar: iverilog -o Clock.v.vvp Clock.v.v
Para executar: vvp Clock.v.vvp
*/

Arq. de Comp. I/Atividades_Guais/2024-2_arq1_guia_09/Guia_0907.v
/*
    -identificação: 

Guia_0907 - 28 / 09 / 2024

Nome: Davi Cândido de Almeida
Matricula: 857859
Código de Pessoa: 1527368

*/


/*

07.) Projetar e descrever em Verilog um módulo
gerador de pulso (pulse) com marcação igual
a 8 unidades de tempo, sincronizado com
o nível alto e estável do gerador do Guia_0900.v.
O nome do arquivo deverá ser Guia_0907.v.
Incluir previsão de testes e verificação da
carta de tempo usando GTKWave.
DICA: Usar always @(clk)

*/


//`include "clock.v" //Colocado manualmente para facilitar visualização

module clock_0900 ( output clk );
    reg clk;
    initial
    begin
        clk = 1'b0;
    end
    always
    begin
    #12 clk = ~clk;
    end
endmodule

module pulse0907 ( signal, clock );
    input clock;
    output signal;
    reg signal;

    always @ ( posedge clock ) //(posedge) Garante uma sincronização apenas com nivel algo - Erro na dica?
    begin
    signal = 1'b1;
    #8 signal = 1'b0;

    end
endmodule // pulse



module Guia_0907;
        wire clock_0900;
        clock_0900 clk ( clock_0900 );

        wire p1_0907;
        pulse0907 pls1 ( p1_0907, clock_0900 );



    initial begin
        $dumpfile ( " Guia_0907.vcd" );
        $dumpvars ( 1, clock_0900, p1_0907 );
         #480 $finish;
end
endmodule // Guia_0907

/*
    -Saídas de resultados:
    

..etc

*/

/*
    -Notas:

Para compilar: iverilog -o Guia_0907.vvp Guia_0907.v
Para executar: vvp Guia_0907.vvp
*/

Arq. de Comp. I/Atividades_Guais/2024-2_arq1_guia_09/Guia_09GTKWave/ Guia_0907.vcd
$date
	Sat Sep 28 09:54:22 2024
$end
$version
	GTKWave Analyzer v3.3.104 (w)1999-2020 BSI
$end
$timescale
	1 s
$end
$scope module Guia_0907 $end
$var wire 1 " clock_0900 $end
$var wire 1 # p1_0907 $end
$upscope $end
$enddefinitions $end
#0
$dumpvars
x#
0"
$end
#12
1"
1#
#20
0#
#24
0"
#36
1"
1#
#44
0#
#48
0"
#60
1"
1#
#68
0#
#72
0"
#84
1"
1#
#92
0#
#96
0"
#108
1"
1#
#116
0#
#120
0"
#132
1"
1#
#140
0#
#144
0"
#156
1"
1#
#164
0#
#168
0"
#180
1"
1#
#188
0#
#192
0"
#204
1"
1#
#212
0#
#216
0"
#228
1"
1#
#236
0#
#240
0"
#252
1"
1#
#260
0#
#264
0"
#276
1"
1#
#284
0#
#288
0"
#300
1"
1#
#308
0#
#312
0"
#324
1"
1#
#332
0#
#336
0"
#348
1"
1#
#356
0#
#360
0"
#372
1"
1#
#380
0#
#384
0"
#396
1"
1#
#404
0#
#408
0"
#420
1"
1#
#428
0#
#432
0"
#444
1"
1#
#452
0#
#456
0"
#468
1"
1#
#476
0#
